envitro/__init__.py
envitro/core.py
envitro/decorators.py
envitro/docker.py
envitro-0.5.0.dist-info/DESCRIPTION.rst
envitro-0.5.0.dist-info/METADATA
envitro-0.5.0.dist-info/RECORD
envitro-0.5.0.dist-info/WHEEL
envitro-0.5.0.dist-info/metadata.json
envitro-0.5.0.dist-info/top_level.txt
