Metadata-Version: 2.0
Name: envitro
Version: 0.5.0
Summary: A module for reading and writing environment variables.
Home-page: https://github.com/MarcMeszaros/envitro
Author: Marc Meszaros
Author-email: me@marcmeszaros.com
License: Apache 2
Keywords: config,environment,12factor
Platform: UNKNOWN
Classifier: Development Status :: 4 - Beta
Classifier: Intended Audience :: Developers
Classifier: License :: OSI Approved :: Apache Software License
Classifier: Programming Language :: Python :: 2
Classifier: Programming Language :: Python :: 2.7
Classifier: Programming Language :: Python :: 3
Classifier: Programming Language :: Python :: 3.3
Classifier: Programming Language :: Python :: 3.4
Classifier: Programming Language :: Python :: 3.5
Classifier: Programming Language :: Python :: 3.6
Provides-Extra: dev
Requires-Dist: wheel; extra == 'dev'
Provides-Extra: test
Requires-Dist: coverage; extra == 'test'
